{
	"version": "https://jsonfeed.org/version/1",
	"title": "Simon's Test Blog",
	"icon": "https://avatars.micro.blog/avatars/2024/10/1583545.jpg",
	"home_page_url": "https://simonpeng-test.micro.blog/",
	"feed_url": "https://simonpeng-test.micro.blog/podcast.json",
	"_podcast": {
		"about": "https://jsonfeed.org/podcasting",
		"image": "https://micro.blog/SimonPeng/podcast.png",
		"explicit": false,
		"categories": [
			{
				"category": "Society \u0026 Culture",
				"subcategory": "Personal Journals"
			}
		]
	},
	"items": [
	]
}
